trainingsample/__init__.py
trainingsample/trainingsample.cpython-313-aarch64-linux-gnu.so
trainingsample-0.2.16.dist-info/METADATA
trainingsample-0.2.16.dist-info/WHEEL
trainingsample-0.2.16.dist-info/licenses/LICENSE
trainingsample-0.2.16.dist-info/RECORD
