Metadata-Version: 2.4
Name: trainingsample
Version: 0.2.16
Classifier: Programming Language :: Rust
Classifier: Programming Language :: Python :: Implementation :: CPython
Classifier: Programming Language :: Python :: Implementation :: PyPy
Classifier: Programming Language :: Python :: 3.11
Classifier: Programming Language :: Python :: 3.12
Classifier: Programming Language :: Python :: 3.13
Requires-Dist: numpy>=1.21.0
Requires-Dist: pillow>=8.0.0
Requires-Dist: pytest>=6.0 ; extra == 'dev'
Requires-Dist: pytest-benchmark ; extra == 'dev'
Requires-Dist: maturin>=1.0,<2.0 ; extra == 'dev'
Requires-Dist: pre-commit ; extra == 'dev'
Provides-Extra: dev
License-File: LICENSE
Summary: High-performance Rust reimplementation of GIL-blocking video/image operations
Author-email: bghira <bghira@users.noreply.github.com>
License: MIT
Requires-Python: >=3.11
